[
  {
    "date": "2025-01-29",
    "theaters": [
      {
        "name": "Kino Atelier",
        "rooms": [
          {
            "name": "Atelier",
            "showings": [
              {
                "time": "17:45",
                "endTime": "19:25",
                "movieId": 44,
                "movieTitle": "Misty – The Erroll Garner Story",
                "attributes": [
                  "2D",
                  "OmdU"
                ],
                "iframeUrl": "https://www.kinoheld.de/kino/tuebingen/kino-atelier-tuebingen/vorstellung/12787?mode=widget"
              },
              {
                "time": "20:00",
                "endTime": "21:45",
                "movieId": 43,
                "movieTitle": "Kneecap",
                "attributes": [
                  "2D",
                  "OmdU"
                ],
                "iframeUrl": "https://www.kinoheld.de/kino/tuebingen/kino-atelier-tuebingen/vorstellung/12780?mode=widget"
              }
            ]
          }
        ]
      }
    ]
  },
  {
    "date": "2025-01-30",
    "theaters": [
      {
        "name": "Kino Blaue Brücke",
        "rooms": [
          {
            "name": "Saal Tarantino",
            "showings": [
              {
                "time": "17:45",
                "endTime": "19:28",
                "movieId": 0,
                "movieTitle": "Paddington in Peru",
                "attributes": [
                  "2D",
                  "OmdU"
                ],
                "iframeUrl": "https://www.kinoheld.de/kino/tuebingen/kino-blaue-bruecke-tuebingen/show/74208?mode=widget&layout=movies&design=new&rb=0&showId=74208"
              },
              {
                "time": "20:15",
                "endTime": "22:09",
                "movieId": 3,
                "movieTitle": "Babygirl",
                "attributes": [
                  "2D",
                  "OmdU"
                ],
                "iframeUrl": "https://www.kinoheld.de/kino/tuebingen/kino-blaue-bruecke-tuebingen/show/74168?mode=widget&layout=movies&design=new&rb=0&showId=74168"
              }
            ]
          },
          {
            "name": "Saal Spielberg",
            "showings": [
              {
                "time": "17:15",
                "endTime": "18:58",
                "movieId": 5,
                "movieTitle": "Sechs Richtige - Glück ist nichts für Anfänger",
                "attributes": [
                  "2D",
                  "OmdU"
                ],
                "iframeUrl": "https://www.kinoheld.de/kino/tuebingen/kino-blaue-bruecke-tuebingen/show/74216?mode=widget&layout=movies&design=new&rb=0&showId=74216"
              },
              {
                "time": "19:30",
                "endTime": "22:23",
                "movieId": 8,
                "movieTitle": "Der Graf von Monte Christo",
                "attributes": [
                  "2D"
                ],
                "iframeUrl": "https://www.kinoheld.de/kino/tuebingen/kino-blaue-bruecke-tuebingen/show/74173?mode=widget&layout=movies&design=new&rb=0&showId=74173"
              }
            ]
          },
          {
            "name": "Saal Kubrick",
            "showings": [
              {
                "time": "17:30",
                "endTime": "19:10",
                "movieId": 2,
                "movieTitle": "Die drei ??? und der Karpatenhund",
                "attributes": [
                  "2D"
                ],
                "iframeUrl": "https://www.kinoheld.de/kino/tuebingen/kino-blaue-bruecke-tuebingen/show/74180?mode=widget&layout=movies&design=new&rb=0&showId=74180"
              },
              {
                "time": "20:00",
                "endTime": "21:54",
                "movieId": 11,
                "movieTitle": "Juror #2",
                "attributes": [
                  "2D"
                ],
                "iframeUrl": "https://www.kinoheld.de/kino/tuebingen/kino-blaue-bruecke-tuebingen/show/74192?mode=widget&layout=movies&design=new&rb=0&showId=74192"
              }
            ]
          }
        ]
      },
      {
        "name": "Kino Museum",
        "rooms": [
          {
            "name": "Saal Almodóvar",
            "showings": [
              {
                "time": "18:00",
                "endTime": "19:43",
                "movieId": 6,
                "movieTitle": "Die leisen und die großen Töne",
                "attributes": [
                  "2D"
                ],
                "iframeUrl": "https://www.kinoheld.de/kino/tuebingen/kino-museum-tuebingen/show/79523?mode=widget&layout=movies&design=new&rb=0&showId=79523"
              },
              {
                "time": "20:15",
                "endTime": "21:58",
                "movieId": 0,
                "movieTitle": "Paddington in Peru",
                "attributes": [
                  "2D"
                ],
                "iframeUrl": "https://www.kinoheld.de/kino/tuebingen/kino-museum-tuebingen/show/79540?mode=widget&layout=movies&design=new&rb=0&showId=79540"
              }
            ]
          },
          {
            "name": "Saal Coppola",
            "showings": [
              {
                "time": "18:00",
                "endTime": "19:36",
                "movieId": 18,
                "movieTitle": "Kundschafter des Friedens 2",
                "attributes": [
                  "2D"
                ],
                "iframeUrl": "https://www.kinoheld.de/kino/tuebingen/kino-museum-tuebingen/show/79533?mode=widget&layout=movies&design=new&rb=0&showId=79533"
              },
              {
                "time": "20:15",
                "endTime": "21:45",
                "movieId": 9,
                "movieTitle": "A Real Pain",
                "attributes": [
                  "2D",
                  "OmdU"
                ],
                "iframeUrl": "https://www.kinoheld.de/kino/tuebingen/kino-museum-tuebingen/show/79519?mode=widget&layout=movies&design=new&rb=0&showId=79519"
              }
            ]
          },
          {
            "name": "Saal Arsenal",
            "showings": [
              {
                "time": "17:15",
                "endTime": "19:34",
                "movieId": 12,
                "movieTitle": "La Cocina - Der Geschmack des Lebens",
                "attributes": [
                  "2D",
                  "OmdU"
                ],
                "iframeUrl": "https://www.kinoheld.de/kino/tuebingen/kino-museum-tuebingen/show/79539?mode=widget&layout=movies&design=new&rb=0&showId=79539"
              }
            ]
          }
        ]
      },
      {
        "name": "Kino Atelier",
        "rooms": [
          {
            "name": "Atelier",
            "showings": [
              {
                "time": "18:00",
                "endTime": "19:45",
                "movieId": 24,
                "movieTitle": "Kneecap",
                "attributes": [
                  "2D",
                  "OmdU"
                ],
                "iframeUrl": "https://www.kinoheld.de/kino/tuebingen/kino-atelier-tuebingen/show/12796?mode=widget&layout=movies&design=new&rb=0&showId=12796"
              },
              {
                "time": "18:00",
                "endTime": "19:45",
                "movieId": 43,
                "movieTitle": "Kneecap",
                "attributes": [
                  "2D",
                  "OmdU"
                ],
                "iframeUrl": "https://www.kinoheld.de/kino/tuebingen/kino-atelier-tuebingen/vorstellung/12796?mode=widget"
              },
              {
                "time": "20:15",
                "endTime": "22:29",
                "movieId": 7,
                "movieTitle": "Nosferatu - Der Untote",
                "attributes": [
                  "2D"
                ],
                "iframeUrl": "https://www.kinoheld.de/kino/tuebingen/kino-atelier-tuebingen/show/12804?mode=widget&layout=movies&design=new&rb=0&showId=12804"
              },
              {
                "time": "20:15",
                "endTime": "22:29",
                "movieId": 45,
                "movieTitle": "Nosferatu - Der Untote",
                "attributes": [
                  "2D"
                ],
                "iframeUrl": "https://www.kinoheld.de/kino/tuebingen/kino-atelier-tuebingen/vorstellung/12804?mode=widget"
              }
            ]
          }
        ]
      }
    ]
  },
  {
    "date": "2025-01-31",
    "theaters": [
      {
        "name": "Kino Blaue Brücke",
        "rooms": [
          {
            "name": "Saal Tarantino",
            "showings": [
              {
                "time": "16:30",
                "endTime": "18:13",
                "movieId": 0,
                "movieTitle": "Paddington in Peru",
                "attributes": [
                  "2D"
                ],
                "iframeUrl": "https://www.kinoheld.de/kino/tuebingen/kino-blaue-bruecke-tuebingen/show/74199?mode=widget&layout=movies&design=new&rb=0&showId=74199"
              },
              {
                "time": "19:00",
                "endTime": "20:43",
                "movieId": 0,
                "movieTitle": "Paddington in Peru",
                "attributes": [
                  "2D"
                ],
                "iframeUrl": "https://www.kinoheld.de/kino/tuebingen/kino-blaue-bruecke-tuebingen/show/74200?mode=widget&layout=movies&design=new&rb=0&showId=74200"
              },
              {
                "time": "21:30",
                "endTime": "23:24",
                "movieId": 3,
                "movieTitle": "Babygirl",
                "attributes": [
                  "2D"
                ],
                "iframeUrl": "https://www.kinoheld.de/kino/tuebingen/kino-blaue-bruecke-tuebingen/show/74165?mode=widget&layout=movies&design=new&rb=0&showId=74165"
              }
            ]
          },
          {
            "name": "Saal Spielberg",
            "showings": [
              {
                "time": "14:45",
                "endTime": "16:25",
                "movieId": 14,
                "movieTitle": "Vaiana 2",
                "attributes": [
                  "2D",
                  "OmdU"
                ],
                "iframeUrl": "https://www.kinoheld.de/kino/tuebingen/kino-blaue-bruecke-tuebingen/show/74222?mode=widget&layout=movies&design=new&rb=0&showId=74222"
              },
              {
                "time": "17:00",
                "endTime": "19:53",
                "movieId": 8,
                "movieTitle": "Der Graf von Monte Christo",
                "attributes": [
                  "2D"
                ],
                "iframeUrl": "https://www.kinoheld.de/kino/tuebingen/kino-blaue-bruecke-tuebingen/show/74174?mode=widget&layout=movies&design=new&rb=0&showId=74174"
              },
              {
                "time": "20:30",
                "endTime": "22:13",
                "movieId": 5,
                "movieTitle": "Sechs Richtige - Glück ist nichts für Anfänger",
                "attributes": [
                  "2D"
                ],
                "iframeUrl": "https://www.kinoheld.de/kino/tuebingen/kino-blaue-bruecke-tuebingen/show/74212?mode=widget&layout=movies&design=new&rb=0&showId=74212"
              }
            ]
          },
          {
            "name": "Saal Kubrick",
            "showings": [
              {
                "time": "15:15",
                "endTime": "16:55",
                "movieId": 2,
                "movieTitle": "Die drei ??? und der Karpatenhund",
                "attributes": [
                  "2D"
                ],
                "iframeUrl": "https://www.kinoheld.de/kino/tuebingen/kino-blaue-bruecke-tuebingen/show/74181?mode=widget&layout=movies&design=new&rb=0&showId=74181"
              },
              {
                "time": "17:45",
                "endTime": "19:25",
                "movieId": 2,
                "movieTitle": "Die drei ??? und der Karpatenhund",
                "attributes": [
                  "2D"
                ],
                "iframeUrl": "https://www.kinoheld.de/kino/tuebingen/kino-blaue-bruecke-tuebingen/show/74182?mode=widget&layout=movies&design=new&rb=0&showId=74182"
              },
              {
                "time": "20:15",
                "endTime": "22:09",
                "movieId": 11,
                "movieTitle": "Juror #2",
                "attributes": [
                  "2D",
                  "OmdU"
                ],
                "iframeUrl": "https://www.kinoheld.de/kino/tuebingen/kino-blaue-bruecke-tuebingen/show/74195?mode=widget&layout=movies&design=new&rb=0&showId=74195"
              }
            ]
          }
        ]
      },
      {
        "name": "Kino Atelier",
        "rooms": [
          {
            "name": "Atelier",
            "showings": [
              {
                "time": "17:15",
                "endTime": "18:50",
                "movieId": 23,
                "movieTitle": "Rabia - Der verlorene Traum",
                "attributes": [
                  "2D"
                ],
                "iframeUrl": "https://www.kinoheld.de/kino/tuebingen/kino-atelier-tuebingen/show/12808?mode=widget&layout=movies&design=new&rb=0&showId=12808"
              },
              {
                "time": "17:15",
                "endTime": "18:50",
                "movieId": 47,
                "movieTitle": "Rabia - Der verlorene Traum",
                "attributes": [
                  "2D"
                ],
                "iframeUrl": "https://www.kinoheld.de/kino/tuebingen/kino-atelier-tuebingen/vorstellung/12808?mode=widget"
              },
              {
                "time": "19:30",
                "endTime": "21:13",
                "movieId": 6,
                "movieTitle": "Die leisen und die großen Töne",
                "attributes": [
                  "2D"
                ],
                "iframeUrl": "https://www.kinoheld.de/kino/tuebingen/kino-atelier-tuebingen/show/12794?mode=widget&layout=movies&design=new&rb=0&showId=12794"
              },
              {
                "time": "19:30",
                "endTime": "21:13",
                "movieId": 46,
                "movieTitle": "Die leisen und die großen Töne",
                "attributes": [
                  "2D"
                ],
                "iframeUrl": "https://www.kinoheld.de/kino/tuebingen/kino-atelier-tuebingen/vorstellung/12794?mode=widget"
              },
              {
                "time": "21:45",
                "endTime": "23:30",
                "movieId": 24,
                "movieTitle": "Kneecap",
                "attributes": [
                  "2D",
                  "OmdU"
                ],
                "iframeUrl": "https://www.kinoheld.de/kino/tuebingen/kino-atelier-tuebingen/show/12797?mode=widget&layout=movies&design=new&rb=0&showId=12797"
              },
              {
                "time": "21:45",
                "endTime": "23:30",
                "movieId": 43,
                "movieTitle": "Kneecap",
                "attributes": [
                  "2D",
                  "OmdU"
                ],
                "iframeUrl": "https://www.kinoheld.de/kino/tuebingen/kino-atelier-tuebingen/vorstellung/12797?mode=widget"
              }
            ]
          }
        ]
      }
    ]
  },
  {
    "date": "2025-02-01",
    "theaters": [
      {
        "name": "Kino Blaue Brücke",
        "rooms": [
          {
            "name": "Saal Tarantino",
            "showings": [
              {
                "time": "14:00",
                "endTime": "15:43",
                "movieId": 0,
                "movieTitle": "Paddington in Peru",
                "attributes": [
                  "2D"
                ],
                "iframeUrl": "https://www.kinoheld.de/kino/tuebingen/kino-blaue-bruecke-tuebingen/show/74201?mode=widget&layout=movies&design=new&rb=0&showId=74201"
              },
              {
                "time": "16:30",
                "endTime": "18:13",
                "movieId": 0,
                "movieTitle": "Paddington in Peru",
                "attributes": [
                  "2D"
                ],
                "iframeUrl": "https://www.kinoheld.de/kino/tuebingen/kino-blaue-bruecke-tuebingen/show/74202?mode=widget&layout=movies&design=new&rb=0&showId=74202"
              },
              {
                "time": "19:00",
                "endTime": "20:43",
                "movieId": 0,
                "movieTitle": "Paddington in Peru",
                "attributes": [
                  "2D"
                ],
                "iframeUrl": "https://www.kinoheld.de/kino/tuebingen/kino-blaue-bruecke-tuebingen/show/74203?mode=widget&layout=movies&design=new&rb=0&showId=74203"
              },
              {
                "time": "21:30",
                "endTime": "23:24",
                "movieId": 3,
                "movieTitle": "Babygirl",
                "attributes": [
                  "2D",
                  "OmdU"
                ],
                "iframeUrl": "https://www.kinoheld.de/kino/tuebingen/kino-blaue-bruecke-tuebingen/show/74169?mode=widget&layout=movies&design=new&rb=0&showId=74169"
              }
            ]
          },
          {
            "name": "Saal Spielberg",
            "showings": [
              {
                "time": "15:30",
                "endTime": "17:10",
                "movieId": 14,
                "movieTitle": "Vaiana 2",
                "attributes": [
                  "2D"
                ],
                "iframeUrl": "https://www.kinoheld.de/kino/tuebingen/kino-blaue-bruecke-tuebingen/show/74218?mode=widget&layout=movies&design=new&rb=0&showId=74218"
              },
              {
                "time": "18:00",
                "endTime": "19:43",
                "movieId": 5,
                "movieTitle": "Sechs Richtige - Glück ist nichts für Anfänger",
                "attributes": [
                  "2D"
                ],
                "iframeUrl": "https://www.kinoheld.de/kino/tuebingen/kino-blaue-bruecke-tuebingen/show/74213?mode=widget&layout=movies&design=new&rb=0&showId=74213"
              },
              {
                "time": "20:15",
                "endTime": "23:08",
                "movieId": 8,
                "movieTitle": "Der Graf von Monte Christo",
                "attributes": [
                  "2D"
                ],
                "iframeUrl": "https://www.kinoheld.de/kino/tuebingen/kino-blaue-bruecke-tuebingen/show/74175?mode=widget&layout=movies&design=new&rb=0&showId=74175"
              }
            ]
          },
          {
            "name": "Saal Kubrick",
            "showings": [
              {
                "time": "15:15",
                "endTime": "16:55",
                "movieId": 2,
                "movieTitle": "Die drei ??? und der Karpatenhund",
                "attributes": [
                  "2D"
                ],
                "iframeUrl": "https://www.kinoheld.de/kino/tuebingen/kino-blaue-bruecke-tuebingen/show/74183?mode=widget&layout=movies&design=new&rb=0&showId=74183"
              },
              {
                "time": "17:45",
                "endTime": "19:25",
                "movieId": 2,
                "movieTitle": "Die drei ??? und der Karpatenhund",
                "attributes": [
                  "2D"
                ],
                "iframeUrl": "https://www.kinoheld.de/kino/tuebingen/kino-blaue-bruecke-tuebingen/show/74184?mode=widget&layout=movies&design=new&rb=0&showId=74184"
              },
              {
                "time": "20:15",
                "endTime": "22:09",
                "movieId": 11,
                "movieTitle": "Juror #2",
                "attributes": [
                  "2D"
                ],
                "iframeUrl": "https://www.kinoheld.de/kino/tuebingen/kino-blaue-bruecke-tuebingen/show/74193?mode=widget&layout=movies&design=new&rb=0&showId=74193"
              }
            ]
          }
        ]
      },
      {
        "name": "Kino Atelier",
        "rooms": [
          {
            "name": "Atelier",
            "showings": [
              {
                "time": "16:45",
                "endTime": "18:30",
                "movieId": 24,
                "movieTitle": "Kneecap",
                "attributes": [
                  "2D",
                  "OmdU"
                ],
                "iframeUrl": "https://www.kinoheld.de/kino/tuebingen/kino-atelier-tuebingen/show/12798?mode=widget&layout=movies&design=new&rb=0&showId=12798"
              },
              {
                "time": "16:45",
                "endTime": "18:30",
                "movieId": 43,
                "movieTitle": "Kneecap",
                "attributes": [
                  "2D",
                  "OmdU"
                ],
                "iframeUrl": "https://www.kinoheld.de/kino/tuebingen/kino-atelier-tuebingen/vorstellung/12798?mode=widget"
              },
              {
                "time": "19:00",
                "endTime": "20:43",
                "movieId": 6,
                "movieTitle": "Die leisen und die großen Töne",
                "attributes": [
                  "2D"
                ],
                "iframeUrl": "https://www.kinoheld.de/kino/tuebingen/kino-atelier-tuebingen/show/12795?mode=widget&layout=movies&design=new&rb=0&showId=12795"
              },
              {
                "time": "19:00",
                "endTime": "20:43",
                "movieId": 46,
                "movieTitle": "Die leisen und die großen Töne",
                "attributes": [
                  "2D"
                ],
                "iframeUrl": "https://www.kinoheld.de/kino/tuebingen/kino-atelier-tuebingen/vorstellung/12795?mode=widget"
              },
              {
                "time": "21:30",
                "endTime": "23:44",
                "movieId": 7,
                "movieTitle": "Nosferatu - Der Untote",
                "attributes": [
                  "2D",
                  "OmdU"
                ],
                "iframeUrl": "https://www.kinoheld.de/kino/tuebingen/kino-atelier-tuebingen/show/12805?mode=widget&layout=movies&design=new&rb=0&showId=12805"
              },
              {
                "time": "21:30",
                "endTime": "23:44",
                "movieId": 45,
                "movieTitle": "Nosferatu - Der Untote",
                "attributes": [
                  "2D",
                  "OmdU"
                ],
                "iframeUrl": "https://www.kinoheld.de/kino/tuebingen/kino-atelier-tuebingen/vorstellung/12805?mode=widget"
              }
            ]
          }
        ]
      }
    ]
  },
  {
    "date": "2025-02-02",
    "theaters": [
      {
        "name": "Kino Blaue Brücke",
        "rooms": [
          {
            "name": "Saal Tarantino",
            "showings": [
              {
                "time": "12:30",
                "endTime": "14:13",
                "movieId": 1,
                "movieTitle": "Пригоди Паддінгтона у Перу",
                "attributes": [
                  "2D"
                ],
                "iframeUrl": "https://www.kinoheld.de/kino/tuebingen/kino-blaue-bruecke-tuebingen/show/74210?mode=widget&layout=movies&design=new&rb=0&showId=74210"
              },
              {
                "time": "15:00",
                "endTime": "16:43",
                "movieId": 0,
                "movieTitle": "Paddington in Peru",
                "attributes": [
                  "2D"
                ],
                "iframeUrl": "https://www.kinoheld.de/kino/tuebingen/kino-blaue-bruecke-tuebingen/show/74204?mode=widget&layout=movies&design=new&rb=0&showId=74204"
              },
              {
                "time": "17:30",
                "endTime": "19:13",
                "movieId": 0,
                "movieTitle": "Paddington in Peru",
                "attributes": [
                  "2D"
                ],
                "iframeUrl": "https://www.kinoheld.de/kino/tuebingen/kino-blaue-bruecke-tuebingen/show/74205?mode=widget&layout=movies&design=new&rb=0&showId=74205"
              },
              {
                "time": "20:00",
                "endTime": "21:54",
                "movieId": 3,
                "movieTitle": "Babygirl",
                "attributes": [
                  "2D",
                  "OmdU"
                ],
                "iframeUrl": "https://www.kinoheld.de/kino/tuebingen/kino-blaue-bruecke-tuebingen/show/74170?mode=widget&layout=movies&design=new&rb=0&showId=74170"
              }
            ]
          },
          {
            "name": "Saal Spielberg",
            "showings": [
              {
                "time": "12:00",
                "endTime": "13:40",
                "movieId": 14,
                "movieTitle": "Vaiana 2",
                "attributes": [
                  "2D"
                ],
                "iframeUrl": "https://www.kinoheld.de/kino/tuebingen/kino-blaue-bruecke-tuebingen/show/74219?mode=widget&layout=movies&design=new&rb=0&showId=74219"
              },
              {
                "time": "14:15",
                "endTime": "15:55",
                "movieId": 14,
                "movieTitle": "Vaiana 2",
                "attributes": [
                  "2D"
                ],
                "iframeUrl": "https://www.kinoheld.de/kino/tuebingen/kino-blaue-bruecke-tuebingen/show/74220?mode=widget&layout=movies&design=new&rb=0&showId=74220"
              },
              {
                "time": "16:45",
                "endTime": "19:38",
                "movieId": 8,
                "movieTitle": "Der Graf von Monte Christo",
                "attributes": [
                  "2D"
                ],
                "iframeUrl": "https://www.kinoheld.de/kino/tuebingen/kino-blaue-bruecke-tuebingen/show/74176?mode=widget&layout=movies&design=new&rb=0&showId=74176"
              },
              {
                "time": "20:15",
                "endTime": "21:58",
                "movieId": 5,
                "movieTitle": "Sechs Richtige - Glück ist nichts für Anfänger",
                "attributes": [
                  "2D",
                  "OmdU"
                ],
                "iframeUrl": "https://www.kinoheld.de/kino/tuebingen/kino-blaue-bruecke-tuebingen/show/74217?mode=widget&layout=movies&design=new&rb=0&showId=74217"
              }
            ]
          },
          {
            "name": "Saal Kubrick",
            "showings": [
              {
                "time": "12:15",
                "endTime": "13:55",
                "movieId": 2,
                "movieTitle": "Die drei ??? und der Karpatenhund",
                "attributes": [
                  "2D"
                ],
                "iframeUrl": "https://www.kinoheld.de/kino/tuebingen/kino-blaue-bruecke-tuebingen/show/74185?mode=widget&layout=movies&design=new&rb=0&showId=74185"
              },
              {
                "time": "14:45",
                "endTime": "16:25",
                "movieId": 2,
                "movieTitle": "Die drei ??? und der Karpatenhund",
                "attributes": [
                  "2D"
                ],
                "iframeUrl": "https://www.kinoheld.de/kino/tuebingen/kino-blaue-bruecke-tuebingen/show/74186?mode=widget&layout=movies&design=new&rb=0&showId=74186"
              },
              {
                "time": "17:15",
                "endTime": "18:55",
                "movieId": 2,
                "movieTitle": "Die drei ??? und der Karpatenhund",
                "attributes": [
                  "2D"
                ],
                "iframeUrl": "https://www.kinoheld.de/kino/tuebingen/kino-blaue-bruecke-tuebingen/show/74187?mode=widget&layout=movies&design=new&rb=0&showId=74187"
              },
              {
                "time": "19:45",
                "endTime": "21:39",
                "movieId": 11,
                "movieTitle": "Juror #2",
                "attributes": [
                  "2D",
                  "OmdU"
                ],
                "iframeUrl": "https://www.kinoheld.de/kino/tuebingen/kino-blaue-bruecke-tuebingen/show/74196?mode=widget&layout=movies&design=new&rb=0&showId=74196"
              }
            ]
          }
        ]
      },
      {
        "name": "Kino Museum",
        "rooms": [
          {
            "name": "Saal Almodóvar",
            "showings": [
              {
                "time": "11:45",
                "endTime": "13:59",
                "movieId": 21,
                "movieTitle": "Better Man - Die Robbie Williams Story",
                "attributes": [
                  "2D"
                ],
                "iframeUrl": "https://www.kinoheld.de/kino/tuebingen/kino-museum-tuebingen/show/79522?mode=widget&layout=movies&design=new&rb=0&showId=79522"
              },
              {
                "time": "14:45",
                "endTime": "16:15",
                "movieId": 9,
                "movieTitle": "A Real Pain",
                "attributes": [
                  "2D"
                ],
                "iframeUrl": "https://www.kinoheld.de/kino/tuebingen/kino-museum-tuebingen/show/79551?mode=widget&layout=movies&design=new&rb=0&showId=79551"
              },
              {
                "time": "17:00",
                "endTime": "18:43",
                "movieId": 6,
                "movieTitle": "Die leisen und die großen Töne",
                "attributes": [
                  "2D"
                ],
                "iframeUrl": "https://www.kinoheld.de/kino/tuebingen/kino-museum-tuebingen/show/79524?mode=widget&layout=movies&design=new&rb=0&showId=79524"
              },
              {
                "time": "19:30",
                "endTime": "21:13",
                "movieId": 0,
                "movieTitle": "Paddington in Peru",
                "attributes": [
                  "2D",
                  "OmdU"
                ],
                "iframeUrl": "https://www.kinoheld.de/kino/tuebingen/kino-museum-tuebingen/show/79544?mode=widget&layout=movies&design=new&rb=0&showId=79544"
              }
            ]
          },
          {
            "name": "Saal Coppola",
            "showings": [
              {
                "time": "11:15",
                "endTime": "13:34",
                "movieId": 12,
                "movieTitle": "La Cocina - Der Geschmack des Lebens",
                "attributes": [
                  "2D"
                ],
                "iframeUrl": "https://www.kinoheld.de/kino/tuebingen/kino-museum-tuebingen/show/79538?mode=widget&layout=movies&design=new&rb=0&showId=79538"
              },
              {
                "time": "14:15",
                "endTime": "15:51",
                "movieId": 18,
                "movieTitle": "Kundschafter des Friedens 2",
                "attributes": [
                  "2D"
                ],
                "iframeUrl": "https://www.kinoheld.de/kino/tuebingen/kino-museum-tuebingen/show/79534?mode=widget&layout=movies&design=new&rb=0&showId=79534"
              },
              {
                "time": "16:30",
                "endTime": "19:11",
                "movieId": 17,
                "movieTitle": "Wicked",
                "attributes": [
                  "2D",
                  "OmdU"
                ],
                "iframeUrl": "https://www.kinoheld.de/kino/tuebingen/kino-museum-tuebingen/show/79550?mode=widget&layout=movies&design=new&rb=0&showId=79550"
              },
              {
                "time": "19:45",
                "endTime": "21:15",
                "movieId": 9,
                "movieTitle": "A Real Pain",
                "attributes": [
                  "2D",
                  "OmdU"
                ],
                "iframeUrl": "https://www.kinoheld.de/kino/tuebingen/kino-museum-tuebingen/show/79520?mode=widget&layout=movies&design=new&rb=0&showId=79520"
              }
            ]
          },
          {
            "name": "Saal Arsenal",
            "showings": [
              {
                "time": "11:30",
                "endTime": "14:17",
                "movieId": 13,
                "movieTitle": "Die Saat des heiligen Feigenbaums",
                "attributes": [
                  "2D"
                ],
                "iframeUrl": "https://www.kinoheld.de/kino/tuebingen/kino-museum-tuebingen/show/79529?mode=widget&layout=movies&design=new&rb=0&showId=79529"
              },
              {
                "time": "14:45",
                "endTime": "17:00",
                "movieId": 15,
                "movieTitle": "Queer",
                "attributes": [
                  "2D"
                ],
                "iframeUrl": "https://www.kinoheld.de/kino/tuebingen/kino-museum-tuebingen/show/79546?mode=widget&layout=movies&design=new&rb=0&showId=79546"
              },
              {
                "time": "17:30",
                "endTime": "19:18",
                "movieId": 10,
                "movieTitle": "We Live in Time",
                "attributes": [
                  "2D"
                ],
                "iframeUrl": "https://www.kinoheld.de/kino/tuebingen/kino-museum-tuebingen/show/79548?mode=widget&layout=movies&design=new&rb=0&showId=79548"
              },
              {
                "time": "19:45",
                "endTime": "21:55",
                "movieId": 16,
                "movieTitle": "Emilia Pérez",
                "attributes": [
                  "2D",
                  "OmdU"
                ],
                "iframeUrl": "https://www.kinoheld.de/kino/tuebingen/kino-museum-tuebingen/show/79531?mode=widget&layout=movies&design=new&rb=0&showId=79531"
              }
            ]
          }
        ]
      },
      {
        "name": "Kino Atelier",
        "rooms": [
          {
            "name": "Atelier",
            "showings": [
              {
                "time": "12:00",
                "endTime": "13:35",
                "movieId": 25,
                "movieTitle": "September 5",
                "attributes": [
                  "2D"
                ],
                "iframeUrl": "https://www.kinoheld.de/kino/tuebingen/kino-atelier-tuebingen/show/12810?mode=widget&layout=movies&design=new&rb=0&showId=12810"
              },
              {
                "time": "12:00",
                "endTime": "13:35",
                "movieId": 48,
                "movieTitle": "September 5",
                "attributes": [
                  "2D"
                ],
                "iframeUrl": "https://www.kinoheld.de/kino/tuebingen/kino-atelier-tuebingen/vorstellung/12810?mode=widget"
              },
              {
                "time": "14:30",
                "endTime": "16:30",
                "movieId": 22,
                "movieTitle": "Konklave",
                "attributes": [
                  "2D"
                ],
                "iframeUrl": "https://www.kinoheld.de/kino/tuebingen/kino-atelier-tuebingen/show/12802?mode=widget&layout=movies&design=new&rb=0&showId=12802"
              },
              {
                "time": "14:30",
                "endTime": "16:30",
                "movieId": 49,
                "movieTitle": "Konklave",
                "attributes": [
                  "2D"
                ],
                "iframeUrl": "https://www.kinoheld.de/kino/tuebingen/kino-atelier-tuebingen/vorstellung/12802?mode=widget"
              },
              {
                "time": "17:00",
                "endTime": "18:45",
                "movieId": 24,
                "movieTitle": "Kneecap",
                "attributes": [
                  "2D",
                  "OmdU"
                ],
                "iframeUrl": "https://www.kinoheld.de/kino/tuebingen/kino-atelier-tuebingen/show/12799?mode=widget&layout=movies&design=new&rb=0&showId=12799"
              },
              {
                "time": "17:00",
                "endTime": "18:45",
                "movieId": 43,
                "movieTitle": "Kneecap",
                "attributes": [
                  "2D",
                  "OmdU"
                ],
                "iframeUrl": "https://www.kinoheld.de/kino/tuebingen/kino-atelier-tuebingen/vorstellung/12799?mode=widget"
              },
              {
                "time": "19:30",
                "endTime": "21:44",
                "movieId": 7,
                "movieTitle": "Nosferatu - Der Untote",
                "attributes": [
                  "2D",
                  "OmdU"
                ],
                "iframeUrl": "https://www.kinoheld.de/kino/tuebingen/kino-atelier-tuebingen/show/12806?mode=widget&layout=movies&design=new&rb=0&showId=12806"
              },
              {
                "time": "19:30",
                "endTime": "21:44",
                "movieId": 45,
                "movieTitle": "Nosferatu - Der Untote",
                "attributes": [
                  "2D",
                  "OmdU"
                ],
                "iframeUrl": "https://www.kinoheld.de/kino/tuebingen/kino-atelier-tuebingen/vorstellung/12806?mode=widget"
              }
            ]
          }
        ]
      }
    ]
  },
  {
    "date": "2025-02-03",
    "theaters": [
      {
        "name": "Kino Blaue Brücke",
        "rooms": [
          {
            "name": "Saal Tarantino",
            "showings": [
              {
                "time": "17:45",
                "endTime": "19:28",
                "movieId": 0,
                "movieTitle": "Paddington in Peru",
                "attributes": [
                  "2D"
                ],
                "iframeUrl": "https://www.kinoheld.de/kino/tuebingen/kino-blaue-bruecke-tuebingen/show/74206?mode=widget&layout=movies&design=new&rb=0&showId=74206"
              },
              {
                "time": "20:15",
                "endTime": "22:09",
                "movieId": 3,
                "movieTitle": "Babygirl",
                "attributes": [
                  "2D"
                ],
                "iframeUrl": "https://www.kinoheld.de/kino/tuebingen/kino-blaue-bruecke-tuebingen/show/74166?mode=widget&layout=movies&design=new&rb=0&showId=74166"
              }
            ]
          },
          {
            "name": "Saal Spielberg",
            "showings": [
              {
                "time": "17:15",
                "endTime": "18:58",
                "movieId": 5,
                "movieTitle": "Sechs Richtige - Glück ist nichts für Anfänger",
                "attributes": [
                  "2D"
                ],
                "iframeUrl": "https://www.kinoheld.de/kino/tuebingen/kino-blaue-bruecke-tuebingen/show/74214?mode=widget&layout=movies&design=new&rb=0&showId=74214"
              },
              {
                "time": "19:30",
                "endTime": "22:23",
                "movieId": 8,
                "movieTitle": "Der Graf von Monte Christo",
                "attributes": [
                  "2D"
                ],
                "iframeUrl": "https://www.kinoheld.de/kino/tuebingen/kino-blaue-bruecke-tuebingen/show/74177?mode=widget&layout=movies&design=new&rb=0&showId=74177"
              }
            ]
          },
          {
            "name": "Saal Kubrick",
            "showings": [
              {
                "time": "17:30",
                "endTime": "19:10",
                "movieId": 2,
                "movieTitle": "Die drei ??? und der Karpatenhund",
                "attributes": [
                  "2D"
                ],
                "iframeUrl": "https://www.kinoheld.de/kino/tuebingen/kino-blaue-bruecke-tuebingen/show/74188?mode=widget&layout=movies&design=new&rb=0&showId=74188"
              },
              {
                "time": "20:00",
                "endTime": "21:54",
                "movieId": 11,
                "movieTitle": "Juror #2",
                "attributes": [
                  "2D",
                  "OmdU"
                ],
                "iframeUrl": "https://www.kinoheld.de/kino/tuebingen/kino-blaue-bruecke-tuebingen/show/74197?mode=widget&layout=movies&design=new&rb=0&showId=74197"
              }
            ]
          }
        ]
      },
      {
        "name": "Kino Museum",
        "rooms": [
          {
            "name": "Saal Almodóvar",
            "showings": [
              {
                "time": "18:00",
                "endTime": "19:43",
                "movieId": 6,
                "movieTitle": "Die leisen und die großen Töne",
                "attributes": [
                  "2D"
                ],
                "iframeUrl": "https://www.kinoheld.de/kino/tuebingen/kino-museum-tuebingen/show/79525?mode=widget&layout=movies&design=new&rb=0&showId=79525"
              },
              {
                "time": "20:15",
                "endTime": "21:58",
                "movieId": 0,
                "movieTitle": "Paddington in Peru",
                "attributes": [
                  "2D"
                ],
                "iframeUrl": "https://www.kinoheld.de/kino/tuebingen/kino-museum-tuebingen/show/79541?mode=widget&layout=movies&design=new&rb=0&showId=79541"
              }
            ]
          },
          {
            "name": "Saal Coppola",
            "showings": [
              {
                "time": "18:00",
                "endTime": "19:36",
                "movieId": 18,
                "movieTitle": "Kundschafter des Friedens 2",
                "attributes": [
                  "2D"
                ],
                "iframeUrl": "https://www.kinoheld.de/kino/tuebingen/kino-museum-tuebingen/show/79535?mode=widget&layout=movies&design=new&rb=0&showId=79535"
              },
              {
                "time": "20:15",
                "endTime": "21:45",
                "movieId": 9,
                "movieTitle": "A Real Pain",
                "attributes": [
                  "2D"
                ],
                "iframeUrl": "https://www.kinoheld.de/kino/tuebingen/kino-museum-tuebingen/show/79516?mode=widget&layout=movies&design=new&rb=0&showId=79516"
              }
            ]
          },
          {
            "name": "Saal Arsenal",
            "showings": [
              {
                "time": "17:15",
                "endTime": "19:30",
                "movieId": 15,
                "movieTitle": "Queer",
                "attributes": [
                  "2D",
                  "OmdU"
                ],
                "iframeUrl": "https://www.kinoheld.de/kino/tuebingen/kino-museum-tuebingen/show/79547?mode=widget&layout=movies&design=new&rb=0&showId=79547"
              },
              {
                "time": "20:00",
                "endTime": "22:00",
                "movieId": 19,
                "movieTitle": "Sneak Preview",
                "attributes": [
                  "2D"
                ],
                "iframeUrl": "https://www.kinoheld.de/kino/tuebingen/kino-museum-tuebingen/show/79545?mode=widget&layout=movies&design=new&rb=0&showId=79545"
              }
            ]
          }
        ]
      },
      {
        "name": "Kino Atelier",
        "rooms": [
          {
            "name": "Atelier",
            "showings": [
              {
                "time": "17:45",
                "endTime": "19:30",
                "movieId": 24,
                "movieTitle": "Kneecap",
                "attributes": [
                  "2D",
                  "OmdU"
                ],
                "iframeUrl": "https://www.kinoheld.de/kino/tuebingen/kino-atelier-tuebingen/show/12800?mode=widget&layout=movies&design=new&rb=0&showId=12800"
              },
              {
                "time": "17:45",
                "endTime": "19:30",
                "movieId": 43,
                "movieTitle": "Kneecap",
                "attributes": [
                  "2D",
                  "OmdU"
                ],
                "iframeUrl": "https://www.kinoheld.de/kino/tuebingen/kino-atelier-tuebingen/vorstellung/12800?mode=widget"
              },
              {
                "time": "20:00",
                "endTime": "22:00",
                "movieId": 22,
                "movieTitle": "Konklave",
                "attributes": [
                  "2D",
                  "OmdU"
                ],
                "iframeUrl": "https://www.kinoheld.de/kino/tuebingen/kino-atelier-tuebingen/show/12803?mode=widget&layout=movies&design=new&rb=0&showId=12803"
              },
              {
                "time": "20:00",
                "endTime": "22:00",
                "movieId": 49,
                "movieTitle": "Konklave",
                "attributes": [
                  "2D",
                  "OmdU"
                ],
                "iframeUrl": "https://www.kinoheld.de/kino/tuebingen/kino-atelier-tuebingen/vorstellung/12803?mode=widget"
              }
            ]
          }
        ]
      }
    ]
  },
  {
    "date": "2025-02-04",
    "theaters": [
      {
        "name": "Kino Blaue Brücke",
        "rooms": [
          {
            "name": "Saal Tarantino",
            "showings": [
              {
                "time": "17:45",
                "endTime": "19:28",
                "movieId": 0,
                "movieTitle": "Paddington in Peru",
                "attributes": [
                  "2D",
                  "OmdU"
                ],
                "iframeUrl": "https://www.kinoheld.de/kino/tuebingen/kino-blaue-bruecke-tuebingen/show/74209?mode=widget&layout=movies&design=new&rb=0&showId=74209"
              },
              {
                "time": "20:15",
                "endTime": "22:09",
                "movieId": 3,
                "movieTitle": "Babygirl",
                "attributes": [
                  "2D"
                ],
                "iframeUrl": "https://www.kinoheld.de/kino/tuebingen/kino-blaue-bruecke-tuebingen/show/74167?mode=widget&layout=movies&design=new&rb=0&showId=74167"
              }
            ]
          },
          {
            "name": "Saal Spielberg",
            "showings": [
              {
                "time": "17:00",
                "endTime": "18:54",
                "movieId": 11,
                "movieTitle": "Juror #2",
                "attributes": [
                  "2D"
                ],
                "iframeUrl": "https://www.kinoheld.de/kino/tuebingen/kino-blaue-bruecke-tuebingen/show/74198?mode=widget&layout=movies&design=new&rb=0&showId=74198"
              },
              {
                "time": "19:30",
                "endTime": "22:23",
                "movieId": 8,
                "movieTitle": "Der Graf von Monte Christo",
                "attributes": [
                  "2D"
                ],
                "iframeUrl": "https://www.kinoheld.de/kino/tuebingen/kino-blaue-bruecke-tuebingen/show/74178?mode=widget&layout=movies&design=new&rb=0&showId=74178"
              }
            ]
          },
          {
            "name": "Saal Kubrick",
            "showings": [
              {
                "time": "17:30",
                "endTime": "19:10",
                "movieId": 2,
                "movieTitle": "Die drei ??? und der Karpatenhund",
                "attributes": [
                  "2D"
                ],
                "iframeUrl": "https://www.kinoheld.de/kino/tuebingen/kino-blaue-bruecke-tuebingen/show/74189?mode=widget&layout=movies&design=new&rb=0&showId=74189"
              },
              {
                "time": "20:00",
                "endTime": "21:53",
                "movieId": 4,
                "movieTitle": "Cliffhanger - Nur die Starken überleben",
                "attributes": [
                  "2D",
                  "OmdU"
                ],
                "iframeUrl": "https://www.kinoheld.de/kino/tuebingen/kino-blaue-bruecke-tuebingen/show/74172?mode=widget&layout=movies&design=new&rb=0&showId=74172"
              }
            ]
          }
        ]
      },
      {
        "name": "Kino Museum",
        "rooms": [
          {
            "name": "Saal Almodóvar",
            "showings": [
              {
                "time": "18:00",
                "endTime": "19:43",
                "movieId": 6,
                "movieTitle": "Die leisen und die großen Töne",
                "attributes": [
                  "2D"
                ],
                "iframeUrl": "https://www.kinoheld.de/kino/tuebingen/kino-museum-tuebingen/show/79526?mode=widget&layout=movies&design=new&rb=0&showId=79526"
              },
              {
                "time": "20:15",
                "endTime": "21:58",
                "movieId": 0,
                "movieTitle": "Paddington in Peru",
                "attributes": [
                  "2D"
                ],
                "iframeUrl": "https://www.kinoheld.de/kino/tuebingen/kino-museum-tuebingen/show/79542?mode=widget&layout=movies&design=new&rb=0&showId=79542"
              }
            ]
          },
          {
            "name": "Saal Coppola",
            "showings": [
              {
                "time": "18:00",
                "endTime": "19:30",
                "movieId": 9,
                "movieTitle": "A Real Pain",
                "attributes": [
                  "2D"
                ],
                "iframeUrl": "https://www.kinoheld.de/kino/tuebingen/kino-museum-tuebingen/show/79517?mode=widget&layout=movies&design=new&rb=0&showId=79517"
              },
              {
                "time": "20:15",
                "endTime": "21:51",
                "movieId": 18,
                "movieTitle": "Kundschafter des Friedens 2",
                "attributes": [
                  "2D"
                ],
                "iframeUrl": "https://www.kinoheld.de/kino/tuebingen/kino-museum-tuebingen/show/79536?mode=widget&layout=movies&design=new&rb=0&showId=79536"
              }
            ]
          },
          {
            "name": "Saal Arsenal",
            "showings": [
              {
                "time": "17:15",
                "endTime": "19:03",
                "movieId": 10,
                "movieTitle": "We Live in Time",
                "attributes": [
                  "2D",
                  "OmdU"
                ],
                "iframeUrl": "https://www.kinoheld.de/kino/tuebingen/kino-museum-tuebingen/show/79549?mode=widget&layout=movies&design=new&rb=0&showId=79549"
              },
              {
                "time": "19:30",
                "endTime": "22:17",
                "movieId": 13,
                "movieTitle": "Die Saat des heiligen Feigenbaums",
                "attributes": [
                  "2D"
                ],
                "iframeUrl": "https://www.kinoheld.de/kino/tuebingen/kino-museum-tuebingen/show/79530?mode=widget&layout=movies&design=new&rb=0&showId=79530"
              }
            ]
          }
        ]
      },
      {
        "name": "Kino Atelier",
        "rooms": [
          {
            "name": "Atelier",
            "showings": [
              {
                "time": "18:00",
                "endTime": "19:35",
                "movieId": 25,
                "movieTitle": "September 5",
                "attributes": [
                  "2D",
                  "OmdU"
                ],
                "iframeUrl": "https://www.kinoheld.de/kino/tuebingen/kino-atelier-tuebingen/show/12811?mode=widget&layout=movies&design=new&rb=0&showId=12811"
              },
              {
                "time": "18:00",
                "endTime": "19:35",
                "movieId": 48,
                "movieTitle": "September 5",
                "attributes": [
                  "2D",
                  "OmdU"
                ],
                "iframeUrl": "https://www.kinoheld.de/kino/tuebingen/kino-atelier-tuebingen/vorstellung/12811?mode=widget"
              },
              {
                "time": "20:00",
                "endTime": "22:14",
                "movieId": 7,
                "movieTitle": "Nosferatu - Der Untote",
                "attributes": [
                  "2D",
                  "OmdU"
                ],
                "iframeUrl": "https://www.kinoheld.de/kino/tuebingen/kino-atelier-tuebingen/show/12807?mode=widget&layout=movies&design=new&rb=0&showId=12807"
              },
              {
                "time": "20:00",
                "endTime": "22:14",
                "movieId": 45,
                "movieTitle": "Nosferatu - Der Untote",
                "attributes": [
                  "2D",
                  "OmdU"
                ],
                "iframeUrl": "https://www.kinoheld.de/kino/tuebingen/kino-atelier-tuebingen/vorstellung/12807?mode=widget"
              }
            ]
          }
        ]
      }
    ]
  },
  {
    "date": "2025-02-05",
    "theaters": [
      {
        "name": "Kino Blaue Brücke",
        "rooms": [
          {
            "name": "Saal Tarantino",
            "showings": [
              {
                "time": "15:15",
                "endTime": "16:58",
                "movieId": 1,
                "movieTitle": "Пригоди Паддінгтона у Перу",
                "attributes": [
                  "2D"
                ],
                "iframeUrl": "https://www.kinoheld.de/kino/tuebingen/kino-blaue-bruecke-tuebingen/show/74211?mode=widget&layout=movies&design=new&rb=0&showId=74211"
              },
              {
                "time": "17:45",
                "endTime": "19:28",
                "movieId": 0,
                "movieTitle": "Paddington in Peru",
                "attributes": [
                  "2D"
                ],
                "iframeUrl": "https://www.kinoheld.de/kino/tuebingen/kino-blaue-bruecke-tuebingen/show/74207?mode=widget&layout=movies&design=new&rb=0&showId=74207"
              },
              {
                "time": "20:15",
                "endTime": "22:09",
                "movieId": 3,
                "movieTitle": "Babygirl",
                "attributes": [
                  "2D",
                  "OmdU"
                ],
                "iframeUrl": "https://www.kinoheld.de/kino/tuebingen/kino-blaue-bruecke-tuebingen/show/74171?mode=widget&layout=movies&design=new&rb=0&showId=74171"
              }
            ]
          },
          {
            "name": "Saal Spielberg",
            "showings": [
              {
                "time": "16:45",
                "endTime": "19:38",
                "movieId": 8,
                "movieTitle": "Der Graf von Monte Christo",
                "attributes": [
                  "2D",
                  "OmdU"
                ],
                "iframeUrl": "https://www.kinoheld.de/kino/tuebingen/kino-blaue-bruecke-tuebingen/show/74179?mode=widget&layout=movies&design=new&rb=0&showId=74179"
              },
              {
                "time": "20:15",
                "endTime": "21:58",
                "movieId": 5,
                "movieTitle": "Sechs Richtige - Glück ist nichts für Anfänger",
                "attributes": [
                  "2D"
                ],
                "iframeUrl": "https://www.kinoheld.de/kino/tuebingen/kino-blaue-bruecke-tuebingen/show/74215?mode=widget&layout=movies&design=new&rb=0&showId=74215"
              }
            ]
          },
          {
            "name": "Saal Kubrick",
            "showings": [
              {
                "time": "15:00",
                "endTime": "16:40",
                "movieId": 2,
                "movieTitle": "Die drei ??? und der Karpatenhund",
                "attributes": [
                  "2D"
                ],
                "iframeUrl": "https://www.kinoheld.de/kino/tuebingen/kino-blaue-bruecke-tuebingen/show/74190?mode=widget&layout=movies&design=new&rb=0&showId=74190"
              },
              {
                "time": "17:30",
                "endTime": "19:10",
                "movieId": 2,
                "movieTitle": "Die drei ??? und der Karpatenhund",
                "attributes": [
                  "2D"
                ],
                "iframeUrl": "https://www.kinoheld.de/kino/tuebingen/kino-blaue-bruecke-tuebingen/show/74191?mode=widget&layout=movies&design=new&rb=0&showId=74191"
              },
              {
                "time": "20:00",
                "endTime": "21:54",
                "movieId": 11,
                "movieTitle": "Juror #2",
                "attributes": [
                  "2D"
                ],
                "iframeUrl": "https://www.kinoheld.de/kino/tuebingen/kino-blaue-bruecke-tuebingen/show/74194?mode=widget&layout=movies&design=new&rb=0&showId=74194"
              }
            ]
          }
        ]
      },
      {
        "name": "Kino Museum",
        "rooms": [
          {
            "name": "Saal Almodóvar",
            "showings": [
              {
                "time": "15:30",
                "endTime": "17:13",
                "movieId": 0,
                "movieTitle": "Paddington in Peru",
                "attributes": [
                  "2D"
                ],
                "iframeUrl": "https://www.kinoheld.de/kino/tuebingen/kino-museum-tuebingen/show/79552?mode=widget&layout=movies&design=new&rb=0&showId=79552"
              },
              {
                "time": "18:00",
                "endTime": "19:43",
                "movieId": 6,
                "movieTitle": "Die leisen und die großen Töne",
                "attributes": [
                  "2D"
                ],
                "iframeUrl": "https://www.kinoheld.de/kino/tuebingen/kino-museum-tuebingen/show/79528?mode=widget&layout=movies&design=new&rb=0&showId=79528"
              },
              {
                "time": "20:15",
                "endTime": "21:58",
                "movieId": 0,
                "movieTitle": "Paddington in Peru",
                "attributes": [
                  "2D"
                ],
                "iframeUrl": "https://www.kinoheld.de/kino/tuebingen/kino-museum-tuebingen/show/79543?mode=widget&layout=movies&design=new&rb=0&showId=79543"
              }
            ]
          },
          {
            "name": "Saal Coppola",
            "showings": [
              {
                "time": "16:00",
                "endTime": "17:30",
                "movieId": 9,
                "movieTitle": "A Real Pain",
                "attributes": [
                  "2D"
                ],
                "iframeUrl": "https://www.kinoheld.de/kino/tuebingen/kino-museum-tuebingen/show/79518?mode=widget&layout=movies&design=new&rb=0&showId=79518"
              },
              {
                "time": "18:00",
                "endTime": "19:36",
                "movieId": 18,
                "movieTitle": "Kundschafter des Friedens 2",
                "attributes": [
                  "2D"
                ],
                "iframeUrl": "https://www.kinoheld.de/kino/tuebingen/kino-museum-tuebingen/show/79537?mode=widget&layout=movies&design=new&rb=0&showId=79537"
              },
              {
                "time": "20:15",
                "endTime": "21:45",
                "movieId": 9,
                "movieTitle": "A Real Pain",
                "attributes": [
                  "2D",
                  "OmdU"
                ],
                "iframeUrl": "https://www.kinoheld.de/kino/tuebingen/kino-museum-tuebingen/show/79521?mode=widget&layout=movies&design=new&rb=0&showId=79521"
              }
            ]
          },
          {
            "name": "Saal Arsenal",
            "showings": [
              {
                "time": "15:45",
                "endTime": "17:28",
                "movieId": 6,
                "movieTitle": "Die leisen und die großen Töne",
                "attributes": [
                  "2D"
                ],
                "iframeUrl": "https://www.kinoheld.de/kino/tuebingen/kino-museum-tuebingen/show/79527?mode=widget&layout=movies&design=new&rb=0&showId=79527"
              },
              {
                "time": "18:00",
                "endTime": "19:30",
                "movieId": 20,
                "movieTitle": "Könige des Sommers",
                "attributes": [
                  "2D"
                ],
                "iframeUrl": "https://www.kinoheld.de/kino/tuebingen/kino-museum-tuebingen/show/79553?mode=widget&layout=movies&design=new&rb=0&showId=79553"
              },
              {
                "time": "20:00",
                "endTime": "22:10",
                "movieId": 16,
                "movieTitle": "Emilia Pérez",
                "attributes": [
                  "2D",
                  "OmdU"
                ],
                "iframeUrl": "https://www.kinoheld.de/kino/tuebingen/kino-museum-tuebingen/show/79532?mode=widget&layout=movies&design=new&rb=0&showId=79532"
              }
            ]
          }
        ]
      },
      {
        "name": "Kino Atelier",
        "rooms": [
          {
            "name": "Atelier",
            "showings": [
              {
                "time": "18:00",
                "endTime": "19:35",
                "movieId": 23,
                "movieTitle": "Rabia - Der verlorene Traum",
                "attributes": [
                  "2D"
                ],
                "iframeUrl": "https://www.kinoheld.de/kino/tuebingen/kino-atelier-tuebingen/show/12809?mode=widget&layout=movies&design=new&rb=0&showId=12809"
              },
              {
                "time": "18:00",
                "endTime": "19:35",
                "movieId": 47,
                "movieTitle": "Rabia - Der verlorene Traum",
                "attributes": [
                  "2D"
                ],
                "iframeUrl": "https://www.kinoheld.de/kino/tuebingen/kino-atelier-tuebingen/vorstellung/12809?mode=widget"
              },
              {
                "time": "20:00",
                "endTime": "21:45",
                "movieId": 24,
                "movieTitle": "Kneecap",
                "attributes": [
                  "2D",
                  "OmdU"
                ],
                "iframeUrl": "https://www.kinoheld.de/kino/tuebingen/kino-atelier-tuebingen/show/12801?mode=widget&layout=movies&design=new&rb=0&showId=12801"
              },
              {
                "time": "20:00",
                "endTime": "21:45",
                "movieId": 43,
                "movieTitle": "Kneecap",
                "attributes": [
                  "2D",
                  "OmdU"
                ],
                "iframeUrl": "https://www.kinoheld.de/kino/tuebingen/kino-atelier-tuebingen/vorstellung/12801?mode=widget"
              }
            ]
          }
        ]
      }
    ]
  },
  {
    "date": "2025-02-07",
    "theaters": [
      {
        "name": "Kino Museum",
        "rooms": [
          {
            "name": "Saal Arsenal",
            "showings": [
              {
                "time": "18:00",
                "endTime": "20:00",
                "movieId": 33,
                "movieTitle": "Die Zeugin - Ihr Weg zurück ins Leben",
                "attributes": [
                  "2D"
                ],
                "iframeUrl": "https://www.kinoheld.de/kino/tuebingen/kino-museum-tuebingen/show/79451?mode=widget&layout=movies&design=new&rb=0&showId=79451"
              }
            ]
          }
        ]
      }
    ]
  },
  {
    "date": "2025-02-10",
    "theaters": [
      {
        "name": "Kino Museum",
        "rooms": [
          {
            "name": "Saal Arsenal",
            "showings": [
              {
                "time": "18:00",
                "endTime": "19:38",
                "movieId": 36,
                "movieTitle": "Goutte d'Or",
                "attributes": [
                  "2D",
                  "OmdU"
                ],
                "iframeUrl": "https://www.kinoheld.de/kino/tuebingen/kino-museum-tuebingen/show/79453?mode=widget&layout=movies&design=new&rb=0&showId=79453"
              }
            ]
          }
        ]
      }
    ]
  },
  {
    "date": "2025-02-11",
    "theaters": [
      {
        "name": "Kino Museum",
        "rooms": [
          {
            "name": "Saal Almodóvar",
            "showings": [
              {
                "time": "20:00",
                "endTime": "22:00",
                "movieId": 35,
                "movieTitle": "Poetry Slam Tübingen",
                "attributes": [
                  "2D"
                ],
                "iframeUrl": "https://www.kinoheld.de/kino/tuebingen/kino-museum-tuebingen/show/79013?mode=widget&layout=movies&design=new&rb=0&showId=79013"
              }
            ]
          }
        ]
      }
    ]
  },
  {
    "date": "2025-02-13",
    "theaters": [
      {
        "name": "Kino Atelier",
        "rooms": [
          {
            "name": "Atelier",
            "showings": [
              {
                "time": "22:00",
                "endTime": "23:55",
                "movieId": 26,
                "movieTitle": "Baby",
                "attributes": [
                  "2D"
                ],
                "iframeUrl": "https://www.kinoheld.de/kino/tuebingen/kino-atelier-tuebingen/show/12774?mode=widget&layout=movies&design=new&rb=0&showId=12774"
              }
            ]
          }
        ]
      }
    ]
  },
  {
    "date": "2025-02-14",
    "theaters": [
      {
        "name": "Kino Museum",
        "rooms": [
          {
            "name": "Saal Arsenal",
            "showings": [
              {
                "time": "19:00",
                "endTime": "20:40",
                "movieId": 37,
                "movieTitle": "Lesung & Gespräch - Uli Burchardt - Menschenschutzgebiet",
                "attributes": [
                  "2D"
                ],
                "iframeUrl": "https://www.kinoheld.de/kino/tuebingen/kino-museum-tuebingen/show/79124?mode=widget&layout=movies&design=new&rb=0&showId=79124"
              }
            ]
          }
        ]
      }
    ]
  },
  {
    "date": "2025-02-20",
    "theaters": [
      {
        "name": "Kino Museum",
        "rooms": [
          {
            "name": "Saal Almodóvar",
            "showings": [
              {
                "time": "20:00",
                "endTime": "21:40",
                "movieId": 31,
                "movieTitle": "DTK unplugged meets Krimispannung live",
                "attributes": [
                  "2D"
                ],
                "iframeUrl": "https://www.kinoheld.de/kino/tuebingen/kino-museum-tuebingen/show/79213?mode=widget&layout=movies&design=new&rb=0&showId=79213"
              }
            ]
          }
        ]
      }
    ]
  },
  {
    "date": "2025-02-21",
    "theaters": [
      {
        "name": "Kino Museum",
        "rooms": [
          {
            "name": "Saal Almodóvar",
            "showings": [
              {
                "time": "20:00",
                "endTime": "21:40",
                "movieId": 31,
                "movieTitle": "DTK unplugged meets Krimispannung live",
                "attributes": [
                  "2D"
                ],
                "iframeUrl": "https://www.kinoheld.de/kino/tuebingen/kino-museum-tuebingen/show/79214?mode=widget&layout=movies&design=new&rb=0&showId=79214"
              }
            ]
          }
        ]
      }
    ]
  },
  {
    "date": "2025-02-23",
    "theaters": [
      {
        "name": "Kino Museum",
        "rooms": [
          {
            "name": "Saal Arsenal",
            "showings": [
              {
                "time": "12:00",
                "endTime": "14:05",
                "movieId": 27,
                "movieTitle": "33 Tage Utopie",
                "attributes": [
                  "2D"
                ],
                "iframeUrl": "https://www.kinoheld.de/kino/tuebingen/kino-museum-tuebingen/show/79452?mode=widget&layout=movies&design=new&rb=0&showId=79452"
              }
            ]
          }
        ]
      }
    ]
  },
  {
    "date": "2025-02-26",
    "theaters": [
      {
        "name": "Kino Museum",
        "rooms": [
          {
            "name": "Saal Almodóvar",
            "showings": [
              {
                "time": "20:00",
                "endTime": "22:00",
                "movieId": 28,
                "movieTitle": "Heldin",
                "attributes": [
                  "2D"
                ],
                "iframeUrl": "https://www.kinoheld.de/kino/tuebingen/kino-museum-tuebingen/show/79454?mode=widget&layout=movies&design=new&rb=0&showId=79454"
              }
            ]
          }
        ]
      }
    ]
  },
  {
    "date": "2025-02-27",
    "theaters": [
      {
        "name": "Kino Museum",
        "rooms": [
          {
            "name": "Saal Almodóvar",
            "showings": [
              {
                "time": "18:00",
                "endTime": "19:52",
                "movieId": 29,
                "movieTitle": "I Am Nevenka",
                "attributes": [
                  "2D",
                  "OmeU"
                ],
                "iframeUrl": "https://www.kinoheld.de/kino/tuebingen/kino-museum-tuebingen/show/79455?mode=widget&layout=movies&design=new&rb=0&showId=79455"
              },
              {
                "time": "20:30",
                "endTime": "22:10",
                "movieId": 30,
                "movieTitle": "The Witness",
                "attributes": [
                  "2D",
                  "OmdU"
                ],
                "iframeUrl": "https://www.kinoheld.de/kino/tuebingen/kino-museum-tuebingen/show/79456?mode=widget&layout=movies&design=new&rb=0&showId=79456"
              }
            ]
          }
        ]
      }
    ]
  },
  {
    "date": "2025-03-13",
    "theaters": [
      {
        "name": "Kino Atelier",
        "rooms": [
          {
            "name": "Atelier",
            "showings": [
              {
                "time": "22:00",
                "endTime": "23:40",
                "movieId": 32,
                "movieTitle": "Layla",
                "attributes": [
                  "2D"
                ],
                "iframeUrl": "https://www.kinoheld.de/kino/tuebingen/kino-atelier-tuebingen/show/12775?mode=widget&layout=movies&design=new&rb=0&showId=12775"
              }
            ]
          }
        ]
      }
    ]
  },
  {
    "date": "2025-03-15",
    "theaters": [
      {
        "name": "Kino Museum",
        "rooms": [
          {
            "name": "Saal Arsenal",
            "showings": [
              {
                "time": "18:00",
                "endTime": "21:05",
                "movieId": 41,
                "movieTitle": "MET Opera 2024/25: Ludwig van Beethoven FIDELIO",
                "attributes": [
                  "2D"
                ],
                "iframeUrl": "https://www.kinoheld.de/kino/tuebingen/kino-museum-tuebingen/show/79391?mode=widget&layout=movies&design=new&rb=0&showId=79391"
              }
            ]
          }
        ]
      }
    ]
  },
  {
    "date": "2025-03-25",
    "theaters": [
      {
        "name": "Kino Museum",
        "rooms": [
          {
            "name": "Saal Almodóvar",
            "showings": [
              {
                "time": "20:00",
                "endTime": "22:30",
                "movieId": 34,
                "movieTitle": "Stand-Up Comedy Slam Tübingen",
                "attributes": [
                  "2D"
                ],
                "iframeUrl": "https://www.kinoheld.de/kino/tuebingen/kino-museum-tuebingen/show/79008?mode=widget&layout=movies&design=new&rb=0&showId=79008"
              }
            ]
          }
        ]
      }
    ]
  },
  {
    "date": "2025-04-01",
    "theaters": [
      {
        "name": "Kino Museum",
        "rooms": [
          {
            "name": "Saal Almodóvar",
            "showings": [
              {
                "time": "19:00",
                "endTime": "20:40",
                "movieId": 38,
                "movieTitle": "Benefizveranstaltung - Rafik Schami - Die Königin und der Kalligraph",
                "attributes": [
                  "2D"
                ],
                "iframeUrl": "https://www.kinoheld.de/kino/tuebingen/kino-museum-tuebingen/show/79395?mode=widget&layout=movies&design=new&rb=0&showId=79395"
              }
            ]
          }
        ]
      }
    ]
  },
  {
    "date": "2025-04-08",
    "theaters": [
      {
        "name": "Kino Museum",
        "rooms": [
          {
            "name": "Saal Almodóvar",
            "showings": [
              {
                "time": "20:00",
                "endTime": "22:00",
                "movieId": 35,
                "movieTitle": "Poetry Slam Tübingen",
                "attributes": [
                  "2D"
                ],
                "iframeUrl": "https://www.kinoheld.de/kino/tuebingen/kino-museum-tuebingen/show/79015?mode=widget&layout=movies&design=new&rb=0&showId=79015"
              }
            ]
          }
        ]
      }
    ]
  },
  {
    "date": "2025-04-26",
    "theaters": [
      {
        "name": "Kino Museum",
        "rooms": [
          {
            "name": "Saal Arsenal",
            "showings": [
              {
                "time": "19:00",
                "endTime": "22:52",
                "movieId": 40,
                "movieTitle": "Met Opera 2024/25: Wolfgang Amadeus Mozart LE NOZZE DI FIGARO",
                "attributes": [
                  "2D"
                ],
                "iframeUrl": "https://www.kinoheld.de/kino/tuebingen/kino-museum-tuebingen/show/79392?mode=widget&layout=movies&design=new&rb=0&showId=79392"
              }
            ]
          }
        ]
      }
    ]
  },
  {
    "date": "2025-05-17",
    "theaters": [
      {
        "name": "Kino Museum",
        "rooms": [
          {
            "name": "Saal Arsenal",
            "showings": [
              {
                "time": "19:00",
                "endTime": "21:15",
                "movieId": 39,
                "movieTitle": "MET Opera 2024/25: Richard Strauss SALOME",
                "attributes": [
                  "2D"
                ],
                "iframeUrl": "https://www.kinoheld.de/kino/tuebingen/kino-museum-tuebingen/show/79393?mode=widget&layout=movies&design=new&rb=0&showId=79393"
              }
            ]
          }
        ]
      }
    ]
  },
  {
    "date": "2025-05-27",
    "theaters": [
      {
        "name": "Kino Museum",
        "rooms": [
          {
            "name": "Saal Almodóvar",
            "showings": [
              {
                "time": "20:00",
                "endTime": "22:30",
                "movieId": 34,
                "movieTitle": "Stand-Up Comedy Slam Tübingen",
                "attributes": [
                  "2D"
                ],
                "iframeUrl": "https://www.kinoheld.de/kino/tuebingen/kino-museum-tuebingen/show/79010?mode=widget&layout=movies&design=new&rb=0&showId=79010"
              }
            ]
          }
        ]
      }
    ]
  },
  {
    "date": "2025-05-31",
    "theaters": [
      {
        "name": "Kino Museum",
        "rooms": [
          {
            "name": "Saal Arsenal",
            "showings": [
              {
                "time": "19:00",
                "endTime": "22:35",
                "movieId": 42,
                "movieTitle": "MET Opera 2024/25: Gioachino Rossini IL BARBIERE DI SIVIGLIA",
                "attributes": [
                  "2D"
                ],
                "iframeUrl": "https://www.kinoheld.de/kino/tuebingen/kino-museum-tuebingen/show/79394?mode=widget&layout=movies&design=new&rb=0&showId=79394"
              }
            ]
          }
        ]
      }
    ]
  },
  {
    "date": "2025-06-10",
    "theaters": [
      {
        "name": "Kino Museum",
        "rooms": [
          {
            "name": "Saal Almodóvar",
            "showings": [
              {
                "time": "20:00",
                "endTime": "22:00",
                "movieId": 35,
                "movieTitle": "Poetry Slam Tübingen",
                "attributes": [
                  "2D"
                ],
                "iframeUrl": "https://www.kinoheld.de/kino/tuebingen/kino-museum-tuebingen/show/79017?mode=widget&layout=movies&design=new&rb=0&showId=79017"
              }
            ]
          }
        ]
      }
    ]
  }
]